smote_cd/__init__.py
smote_cd/dataset_generation.py
smote_cd/main.py
smote_cd/setup.py
smote_cd-0.2.1.dist-info/LICENSE.txt
smote_cd-0.2.1.dist-info/METADATA
smote_cd-0.2.1.dist-info/WHEEL
smote_cd-0.2.1.dist-info/top_level.txt
smote_cd-0.2.1.dist-info/RECORD
